jupyter_fortran_kernel/__init__.py
jupyter_fortran_kernel/__main__.py
jupyter_fortran_kernel/kernel.py
jupyter_fortran_kernel-0.1.0.dist-info/DESCRIPTION.rst
jupyter_fortran_kernel-0.1.0.dist-info/METADATA
jupyter_fortran_kernel-0.1.0.dist-info/RECORD
jupyter_fortran_kernel-0.1.0.dist-info/WHEEL
jupyter_fortran_kernel-0.1.0.dist-info/metadata.json
jupyter_fortran_kernel-0.1.0.dist-info/top_level.txt
